pydysp/__init__.py
pydysp/channel.py
pydysp/test.py
pyDySP-0.1.3.dist-info/LICENSE
pyDySP-0.1.3.dist-info/METADATA
pyDySP-0.1.3.dist-info/WHEEL
pyDySP-0.1.3.dist-info/top_level.txt
pyDySP-0.1.3.dist-info/RECORD
