Metadata-Version: 2.1
Name: pyDySP
Version: 0.1.3
Summary: Python Dynamic Signal Processing
Author-email: Dr Dimitris Karamitros <d.karamitros@bristol.ac.uk>
Project-URL: Homepage, https://github.com/dkaramitros/pyDySP
Project-URL: Documentation, https://pydysp.readthedocs.io/
Classifier: Development Status :: 3 - Alpha
Classifier: Intended Audience :: Science/Research
Classifier: Topic :: Scientific/Engineering
Classifier: License :: OSI Approved :: MIT License
Classifier: Programming Language :: Python :: 3
Requires-Python: >=3.8
License-File: LICENSE
Requires-Dist: numpy
Requires-Dist: scipy
Requires-Dist: matplotlib
